smtputility/__init__.py
smtputility/default_table_style.py
smtputility/email_with_attachments.py
smtputility/email_without_attachment.py
smtputility/notify_error.py
smtputility-1.3.dist-info/LICENSE
smtputility-1.3.dist-info/METADATA
smtputility-1.3.dist-info/WHEEL
smtputility-1.3.dist-info/top_level.txt
smtputility-1.3.dist-info/RECORD
