Metadata-Version: 2.1
Name: smtputility
Version: 1.3
Summary: SMTP email automation functions
Home-page: https://github.com/MattDJensen/SMTP_Utility_Package
Author: Matthew Jensen
Author-email: matt@matthewjensen.dev
License: MIT
Download-URL: https://github.com/MattDJensen/SMTP_Utility_Package/archive/1.3.tar.gz
Platform: UNKNOWN
Classifier: License :: OSI Approved :: MIT License
Classifier: Programming Language :: Python :: 3
Classifier: Programming Language :: Python :: 3.8
Classifier: Operating System :: OS Independent
Requires-Python: >=3.6
